PC_Adder.v
module PC_Adder(
    input [18:0] a,
    input [18:0] b,
    output [18:0] c
);

assign c= a + b;

endmodule

Mux.v
module Mux(
    input [18:0] a,
    input [18:0] b,
    input s,
    output [18:0] c
);

assign c = s ? b : a;

endmodule

Data_Memory.v
module Data_Memory(
    input clk,
    input rst,
    input WE,
    input [18:0] WD,
    input [18:0] A,
    output [18:0] RD
);

reg [18:0] mem [0:1023];
always @(posedge clk) begin
    if(WE)
        mem[A] <= WD;
end

assign RD = (!rst) ? 19'd0 : mem[A];

initial begin
    mem[30] = 19'd99;
end

endmodule

ALU.v
module ALU(
    input [18:0] A
    input [18:0] B,
    output [18:0] Result,
    input [4:0] ALUControl
    output Negative
);

assign Sum = A + B;
assign Diff = A - B;
assign mult_full = A*B;
assign Prod = mult_full[18:0];
assign Quot = (B!=0)? (A/B): 19'b0;
assign AndOp = A & B;
assign OrOp = A | B;
assign XorOp = A ^ B;
assign NotOp = ~A;
assign Inc = A + 1;
assign Dec = A -1;


assign Result = (ALUControl == 5'b00000)? Sum:
                (ALUControl == 5'b00001)? Diff:
                (ALUControl == 5'b00010)? Prod:
                (ALUControl == 5'b00011)? Quot:
                (ALUControl == 5'b00100)? Inc:
                (ALUControl == 5'b00101)? Dec:
                (ALUControl == 5'b00110)? AndOp:
                (ALUControl == 5'b00111)? OrOp:
                (ALUControl == 5'b01000)? XorOp:
                (ALUControl == 5'b01001)? NotOp:
                (ALUControl == 5'b01010)? 19'd0: // FFt
                (ALUControl == 5'b01011)? 19'd0: //Encrypt
                (ALUControl == 5'b01100)? 19'd0: //Decrypt
                19'd0

endmodule

assign Negative = Result[18];

Sign_Extend.v
module Sign_Extend(
    input [7:0] imm_in,
    output [18:0] imm_out
);

assign imm_out = {{11{imm_in[7]}}, imm_in};

endmodule

ALU_Decoder.v
module ALU_Decoder(
    input [1:0] ALUOp,
    input [4:0] funct,
    output [4:0] ALUControl
);

assign ALUControl = (ALUOp == 2'b00) ? funct : 5'b00000;

endmodule

Main_Decoder.v
module Main_Decoder(
    input [4:0] Op,
    output RegWrite,
    output ALUSrc,
    output MemWrite,
    output ResultSrc,
    output Branch,
    output Jump,
    output Call,
    output Ret,
    output [1:0] ImmSrc,
    output [1:0] ALUOp
);

reg regwrite, alusrc, memwrite,resultsrc,branch,jump,call,ret;
reg [1:0] immsrc;
reg [1:0] alu_op;


always @(*) begin
    case(Op)
        5'b00000: begin // R type instructions
            regwrite=1; 
            alusrc=0;
            memwrite=0;
            resultsrc=0;
            branch=0;
            jump=0;
            call=0;
            ret=0;
            immsrc = 2'b00;
            alu_op=2'b00;
        end

        5'b00001: begin // I type instructions
            regwrite=1; 
            alusrc=1;
            memwrite=0;
            resultsrc=1;
            branch=0;
            jump=0;
            call=0;
            ret=0;
            immsrc = 2'b01;
            alu_op=2'b00;
        end

        5'b00010: begin // S type instructions
            regwrite=0; 
            alusrc=1;
            memwrite=1;
            resultsrc=0;
            branch=0;
            jump=0;
            call=0;
            ret=0;
            immsrc = 2'b01;
            alu_op=2'b00;
        end

        5'b00011: begin // BEQ type instructions
            regwrite=0; 
            alusrc=0;
            memwrite=0;
            resultsrc=0;
            branch=1;
            jump=0;
            call=0;
            ret=0;
            immsrc = 2'b01;
            alu_op=2'b00;
        end

        5'b00100: begin // BNE type instructions
            regwrite=1; 
            alusrc=0;
            memwrite=0;
            resultsrc=0;
            branch=1;
            jump=0;
            call=0;
            ret=0;
            immsrc = 2'b01;
            alu_op=2'b00;
        end

        5'b00101: begin // JMP type instructions
            regwrite=0; 
            alusrc=0;
            memwrite=0;
            resultsrc=0;
            branch=0;
            jump=1;
            call=0;
            ret=0;
            immsrc = 2'b10;
            alu_op=2'b00;
        end

        5'b00110: begin // CALL type instructions
            regwrite=0; 
            alusrc=0;
            memwrite=0;
            resultsrc=0;
            branch=0;
            jump=1;
            call=1;
            ret=0;
            immsrc = 2'b10;
            alu_op=2'b00;
        end

        5'b00111: begin // Ret type instructions
            regwrite=0; 
            alusrc=0;
            memwrite=0;
            resultsrc=0;
            branch=0;
            jump=1;
            call=0;
            ret=1;
            immsrc = 2'b00;
            alu_op=2'b00;
        end

        default: begin
            regwrite=0; 
            alusrc=0;
            memwrite=0;
            resultsrc=0;
            branch=0;
            jump=0;
            call=0;
            ret=0;
            immsrc = 2'b00;
            alu_op=2'b00;
        end
    endcase
end

assign RegWrite = regwrite;
assign ALUSrc = alusrc;
assign MemWrite= memwrite;
assign ResultSrc = resultsrc;
assign Branch = branch;
assign Jump = jump;
assign Call = call;
assign Ret = ret;
assign ImmSrc = immsrc;
assign ALUOp = alu_op;


endmodule

Register_File.v
module Register_File(
    input clk,
    input rst,
    input WE3,
    input [18:0] WD3,
    input [2:0] A1,
    input [2:0] A2,
    input [2:0] A3,
    output [18:0] RD1,
    output [18:0] RD2
);

reg [18:0] Register [0:7];
always @(posedge clk) begin
    if(WE3)
        Register[A3] <= WD3;
end

assign RD1 = (!rst) ? 19'd0 : Register[A1];
assign RD2 = (!rst) ? 19'd0 : Register[A2];

initial begin
    Register[2] = 19'd5;
    Register[3] = 19'd3;
    Register[5] = 19'd20;
    Register[7] = 19'd40;
    Register[6] = 19'd77;
end

endmodule

Instruction_Memory.v
module Instruction_Memory(
    input rst,
    input [18:0] A,
    output [18:0] RD
);

reg [18:0] mem [0:127];
assign RD = (!rst) ? 19'd0 : mem[A];

initial begin
        //ADD
        mem[0] = {5'b00000, 3'd1, 3'd2, 3'd3, 5'b00000};
        //LD
        mem[1] = {5'b00001, 3'd4, 3'd5, 8'd10};
        //ST
        mem[2] = {5'b00010, 3'd7, 3'd6, 8'd20};
        //BEQ
        mem[3] = {5'b00011, 3'd2, 3'd2, 8'd3};
        //SUB
        mem[4] = {5'b00000, 3'd1, 3'd2, 3'd3, 5'b00001};
        //BNE
        mem[5] = {5'b00100, 3'd2, 3'd3, 8'b11111110};
        //JMP
        mem[6] = {5'b00101, 14'd8};
        //CALL
        mem[7] = {5'b00110, 14'd10};
        //MUL
        mem[8] = {5'b00000, 3'd1, 3'd2, 3'd3, 5'b00010};
        //RET
        mem[9] = {5'b00111, 14'd0};

end

endmodule

PC_Module.v
module PC_Module(
    input clk,
    input rst,
    output [18:0] PC,
    input [18:0] PC_Next
);

reg [18:0] PC_reg;
assign PC = PC_reg;
always @(posedge clk) begin
    if(!rst)
        PC_reg <= 19'd0;
    else
        PC_reg <= PC_Next;
end

endmodule

Single_Cycle_Top.v
`include "PC_Module.v"
`include "PC_Adder.v"
`include "Instruction_Memory.v"
`include "Register_File.v"
`include "Sign_Extend.v"
`include "ALU.v"
`include "ALU_Decoder.v"
`include "Main_Decoder.v"
`include "Data_Memory.v"
`include "Mux.v"

module Single_Cycle_Top(
    input clk,
    input rst
);
    // Program Counter signals.
    wire [18:0] PC;
    reg  [18:0] PC_Next;
    wire [18:0] PC_Plus1;
    PC_Module PC_Mod(.clk(clk), .rst(rst), .PC(PC), .PC_Next(PC_Next));
    PC_Adder PC_Add(.a(PC), .b(19'd1), .c(PC_Plus1));
    
    // Fetch Instruction.
    wire [18:0] Instr;
    Instruction_Memory IM(.rst(rst), .A(PC), .RD(Instr));
    
    wire [4:0] opcode;
    assign opcode = Instr[18:14];
    
    // Instruction type flags.
    wire isR   = (opcode == 5'b00000);
    wire isI   = (opcode == 5'b00001);
    wire isS   = (opcode == 5'b00010);
    wire isBEQ = (opcode == 5'b00011);
    wire isBNE = (opcode == 5'b00100);
    wire isJMP = (opcode == 5'b00101);
    wire isCALL= (opcode == 5'b00110);
    wire isRET = (opcode == 5'b00111);
    
    wire [2:0] reg_rd, reg_rs1, reg_rs2;
    wire [4:0] funct;
    wire [7:0] imm_field;
    wire [13:0] jump_imm;
    
    assign jump_imm = Instr[13:0];
    assign imm_field = (!isR && !isJMP && !isCALL && !isRET) ? Instr[7:0] : 8'd0;
    assign reg_rd  = isR ? Instr[13:11] : (isI ? Instr[13:11] : 3'd0);
    assign reg_rs1 = (isR || isI) ? Instr[10:8] : ((isS || isBEQ || isBNE) ? Instr[13:11] : 3'd0);
    assign reg_rs2 = isR ? Instr[7:5]  : ((isS || isBEQ || isBNE) ? Instr[10:8] : 3'd0);
    assign funct   = isR ? Instr[4:0]  : 5'b00000; 
    
    // Register File.
    wire [18:0] RD1, RD2;
    Register_File RF(
        .clk(clk),
        .rst(rst),
        .WE3(RegWrite),
        .WD3(Result),
        .A1(reg_rs1),
        .A2(reg_rs2),
        .A3(reg_rd),
        .RD1(RD1),
        .RD2(RD2)
    );
    
    // Control Unit.
    wire RegWrite, ALUSrc, MemWrite, ResultSrc, Branch, Jump, Call, Ret;
    wire [1:0] ImmSrc, ALUOp;
    Main_Decoder MD(
        .Op(opcode),
        .RegWrite(RegWrite),
        .ALUSrc(ALUSrc),
        .MemWrite(MemWrite),
        .ResultSrc(ResultSrc),
        .Branch(Branch),
        .Jump(Jump),
        .Call(Call),
        .Ret(Ret),
        .ImmSrc(ImmSrc),
        .ALUOp(ALUOp)
    );
    
    // ALU Decoder.
    wire [4:0] effective_funct;
    assign effective_funct = isR ? funct : 5'b00000;
    wire [4:0] ALUControl;
    ALU_Decoder AD(
        .ALUOp(ALUOp),
        .funct(effective_funct),
        .ALUControl(ALUControl)
    );
    
    // Sign extension for I/S/Branch immediate.
    wire [18:0] imm_extended;
    Sign_Extend SE(
        .imm_in(imm_field),
        .imm_out(imm_extended)
    );
    
    // Select ALU second operand:
    // For R-type: use RD2; for I/S-type: use immediate.
    wire [18:0] alu_in2;
    Mux Mux_ALU(
        .a(RD2),
        .b(imm_extended),
        .s(ALUSrc),
        .c(alu_in2)
    );
    
    // ALU.
    wire [18:0] ALU_Result;
    ALU ALU_inst(
        .A(RD1),
        .B(alu_in2),
        .ALUControl(ALUControl),
        .Result(ALU_Result),
        .Negative()
    );
    
    // Data Memory.
    wire [18:0] Mem_Read;
    Data_Memory DM(
        .clk(clk),
        .rst(rst),
        .WE(MemWrite),
        .WD(RD2), // For store, data comes from RD2.
        .A(ALU_Result),
        .RD(Mem_Read)
    );
    
    // Write-back multiplexer.
    wire [18:0] Result;
    Mux Mux_Result(
        .a(ALU_Result),
        .b(Mem_Read),
        .s(ResultSrc),
        .c(Result)
    );
    

    wire [18:0] branch_target;
    PC_Adder PC_Branch(.a(PC), .b(imm_extended), .c(branch_target));
    
    wire [18:0] jump_target;
    assign jump_target = {5'd0, jump_imm};
    
    // Determine branch condition.
    wire branch_taken;
    assign branch_taken = (isBEQ && (RD1 == RD2)) || (isBNE && (RD1 != RD2));
    
    // PC Next MUX
    reg [18:0] next_PC;
    always @(*) begin
        if (isRET)
            next_PC = call_stack[sp-1];  
        else if (isCALL || isJMP)
            next_PC = jump_target;       
        else if (isBEQ || isBNE)
            next_PC = branch_taken ? branch_target : PC_Plus1;
        else
            next_PC = PC_Plus1;
    end
    always @(*) begin
        PC_Next = next_PC;
    end
    

    reg [18:0] call_stack [0:15];
    reg [3:0] sp;
    integer i;
    
    always @(posedge clk) begin
        if (!rst) begin
            sp <= 0;
            for (i = 0; i < 16; i = i + 1)
                call_stack[i] <= 19'd0;
        end else begin
            if (isCALL) begin
                call_stack[sp] <= PC_Plus1; 
                sp <= sp + 1;
            end else if (isRET) begin
                sp <= sp - 1; 
            end
        end
    end
    
endmodule

Single_Cycle_Top_Tb.v
module Single_Cycle_Top_tb();

reg clk=1'b1,rst;

Single_Cycle_Top Single_Cycle_Top(
    .clk(clk),
    .rst(rst)
);

initial begin
    $dumpfile("Single Cycle.vcd");
    $dumpvars(0);
end

always begin
    clk = ~clk;
    #50;
end

initial begin 
    rst <= 1'b0;
    #50;

    rst<= 1'b1;
    #800;
    $finish;
end

endmodule

Single Cycle.vcd
$date
	Sun Feb 09 12:04:43 2025
$end
$version
	Icarus Verilog
$end
$timescale
	1s
$end
$scope module Single_Cycle_Top_tb $end
$var reg 1 ! clk $end
$var reg 1 " rst $end
$scope module Single_Cycle_Top $end
$var wire 1 # branch_taken $end
$var wire 1 ! clk $end
$var wire 1 " rst $end
$var wire 3 $ reg_rs2 [2:0] $end
$var wire 3 % reg_rs1 [2:0] $end
$var wire 3 & reg_rd [2:0] $end
$var wire 5 ' opcode [4:0] $end
$var wire 19 ( jump_target [18:0] $end
$var wire 14 ) jump_imm [13:0] $end
$var wire 1 * isS $end
$var wire 1 + isRET $end
$var wire 1 , isR $end
$var wire 1 - isJMP $end
$var wire 1 . isI $end
$var wire 1 / isCALL $end
$var wire 1 0 isBNE $end
$var wire 1 1 isBEQ $end
$var wire 8 2 imm_field [7:0] $end
$var wire 19 3 imm_extended [18:0] $end
$var wire 5 4 funct [4:0] $end
$var wire 5 5 effective_funct [4:0] $end
$var wire 19 6 branch_target [18:0] $end
$var wire 19 7 alu_in2 [18:0] $end
$var wire 1 8 Ret $end
$var wire 1 9 ResultSrc $end
$var wire 19 : Result [18:0] $end
$var wire 1 ; RegWrite $end
$var wire 19 < RD2 [18:0] $end
$var wire 19 = RD1 [18:0] $end
$var wire 19 > PC_Plus1 [18:0] $end
$var wire 19 ? PC [18:0] $end
$var wire 19 @ Mem_Read [18:0] $end
$var wire 1 A MemWrite $end
$var wire 1 B Jump $end
$var wire 19 C Instr [18:0] $end
$var wire 2 D ImmSrc [1:0] $end
$var wire 1 E Call $end
$var wire 1 F Branch $end
$var wire 19 G ALU_Result [18:0] $end
$var wire 1 H ALUSrc $end
$var wire 2 I ALUOp [1:0] $end
$var wire 5 J ALUControl [4:0] $end
$var reg 19 K PC_Next [18:0] $end
$var reg 19 L next_PC [18:0] $end
$var reg 4 M sp [3:0] $end
$var integer 32 N i [31:0] $end
$scope module AD $end
$var wire 5 O funct [4:0] $end
$var wire 2 P ALUOp [1:0] $end
$var wire 5 Q ALUControl [4:0] $end
$upscope $end
$scope module ALU_inst $end
$var wire 5 R ALUControl [4:0] $end
$var wire 19 S AndOp [18:0] $end
$var wire 19 T NotOp [18:0] $end
$var wire 19 U OrOp [18:0] $end
$var wire 19 V XorOp [18:0] $end
$var wire 38 W mult_full [37:0] $end
$var wire 19 X Sum [18:0] $end
$var wire 19 Y Result [18:0] $end
$var wire 19 Z Quot [18:0] $end
$var wire 19 [ Prod [18:0] $end
$var wire 1 \ Negative $end
$var wire 19 ] Inc [18:0] $end
$var wire 19 ^ Diff [18:0] $end
$var wire 19 _ Dec [18:0] $end
$var wire 19 ` B [18:0] $end
$var wire 19 a A [18:0] $end
$upscope $end
$scope module DM $end
$var wire 19 b A [18:0] $end
$var wire 1 ! clk $end
$var wire 1 " rst $end
$var wire 1 A WE $end
$var wire 19 c WD [18:0] $end
$var wire 19 d RD [18:0] $end
$upscope $end
$scope module IM $end
$var wire 1 " rst $end
$var wire 19 e RD [18:0] $end
$var wire 19 f A [18:0] $end
$upscope $end
$scope module MD $end
$var wire 1 F Branch $end
$var wire 1 E Call $end
$var wire 2 g ImmSrc [1:0] $end
$var wire 1 B Jump $end
$var wire 1 A MemWrite $end
$var wire 5 h Op [4:0] $end
$var wire 1 ; RegWrite $end
$var wire 1 8 Ret $end
$var wire 1 9 ResultSrc $end
$var wire 1 H ALUSrc $end
$var wire 2 i ALUOp [1:0] $end
$var reg 2 j alu_op [1:0] $end
$var reg 1 H alusrc $end
$var reg 1 k branch $end
$var reg 1 l call $end
$var reg 2 m immsrc [1:0] $end
$var reg 1 n jump $end
$var reg 1 o memwrite $end
$var reg 1 p regwrite $end
$var reg 1 9 resultsrc $end
$var reg 1 q ret $end
$upscope $end
$scope module Mux_ALU $end
$var wire 1 H s $end
$var wire 19 r c [18:0] $end
$var wire 19 s b [18:0] $end
$var wire 19 t a [18:0] $end
$upscope $end
$scope module Mux_Result $end
$var wire 19 u a [18:0] $end
$var wire 19 v b [18:0] $end
$var wire 1 9 s $end
$var wire 19 w c [18:0] $end
$upscope $end
$scope module PC_Add $end
$var wire 19 x b [18:0] $end
$var wire 19 y c [18:0] $end
$var wire 19 z a [18:0] $end
$upscope $end
$scope module PC_Branch $end
$var wire 19 { c [18:0] $end
$var wire 19 | b [18:0] $end
$var wire 19 } a [18:0] $end
$upscope $end
$scope module PC_Mod $end
$var wire 19 ~ PC_Next [18:0] $end
$var wire 1 ! clk $end
$var wire 1 " rst $end
$var wire 19 !" PC [18:0] $end
$var reg 19 "" PC_reg [18:0] $end
$upscope $end
$scope module RF $end
$var wire 3 #" A1 [2:0] $end
$var wire 3 $" A2 [2:0] $end
$var wire 3 %" A3 [2:0] $end
$var wire 19 &" WD3 [18:0] $end
$var wire 1 ; WE3 $end
$var wire 1 ! clk $end
$var wire 1 " rst $end
$var wire 19 '" RD2 [18:0] $end
$var wire 19 (" RD1 [18:0] $end
$upscope $end
$scope module SE $end
$var wire 8 )" imm_in [7:0] $end
$var wire 19 *" imm_out [18:0] $end
$upscope $end
$upscope $end
$upscope $end
$enddefinitions $end
$comment Show the parameter values. $end
$dumpall
$end
#0
$dumpvars
b0 *"
b0 )"
b0 ("
b0 '"
b0 &"
b0 %"
b0 $"
b0 #"
bx ""
bx !"
bx ~
bx }
b0 |
bx {
bx z
bx y
b1 x
b0 w
b0 v
b0 u
b0 t
b0 s
b0 r
0q
1p
0o
0n
b0 m
0l
0k
b0 j
b0 i
b0 h
b0 g
bx f
b0 e
b0 d
b0 c
b0 b
b0 a
b0 `
b1111111111111111111 _
b0 ^
b1 ]
0\
b0 [
b0 Z
b0 Y
b0 X
b0 W
b0 V
b0 U
b1111111111111111111 T
b0 S
b0 R
b0 Q
b0 P
b0 O
bx N
bx M
bx L
bx K
b0 J
b0 I
0H
b0 G
0F
0E
b0 D
b0 C
0B
0A
b0 @
bx ?
bx >
b0 =
b0 <
1;
b0 :
09
08
b0 7
bx 6
b0 5
b0 4
b0 3
b0 2
01
00
0/
0.
0-
1,
0+
0*
b0 )
b0 (
b0 '
b0 &
b0 %
b0 $
0#
0"
0!
$end
#50
b1 Z
b1111 [
b1 S
b1000 :
b1000 w
b1000 &"
b1111 W
b11 7
b11 `
b11 r
b1000 G
b1000 Y
b1000 b
b1000 u
b1111111111111111010 T
b110 V
b111 U
b11 <
b11 c
b11 t
b11 '"
b100 _
b110 ]
b10 ^
b1000 X
b101 =
b101 a
b101 ("
b11 $
b11 $"
b10 %
b10 #"
b1 &
b1 %"
b1 K
b1 ~
b101001100000 (
b101001100000 )
b1 L
bx @
bx d
bx v
b101001100000 C
b101001100000 e
b0 M
b0 6
b0 {
b1 >
b1 y
b0 ?
b0 f
b0 z
b0 }
b0 !"
b0 ""
1"
b10000 N
1!
#100
0!
#150
b1100011 @
b1100011 d
b1100011 v
b1010 3
b1010 s
b1010 |
b1010 *"
b1010 2
b1010 )"
b1111111111111101011 T
b10 Z
b11001000 [
b11110 G
b11110 Y
b11110 b
b11110 u
b11110 V
b11110 U
b0 S
b10011 _
b10101 ]
b10100 =
b10100 a
b10100 ("
b0 <
b0 c
b0 t
b0 '"
b1100011 :
b1100011 w
b1100011 &"
b11001000 W
b1010 ^
b11110 X
b1010 7
b1010 `
b1010 r
b101 %
b101 #"
b100 &
b100 %"
b0 $
b0 $"
b1 D
b1 g
b1 m
19
1H
b10 K
b10 ~
b10010100001010 (
b10010100001010 )
0,
1.
b1 '
b1 h
b10 L
b110010100001010 C
b110010100001010 e
b1011 6
b1011 {
b10 >
b10 y
b1 ?
b1 f
b1 z
b1 }
b1 !"
b1 ""
1!
#200
0!
#250
b1001101 <
b1001101 c
b1001101 t
b1001101 '"
bx @
bx d
bx v
b110 $
b110 $"
b1111111111111010111 T
b10 Z
b1100100000 [
b111100 G
b111100 Y
b111100 b
b111100 u
b111100 V
b111100 U
b100111 _
b101001 ]
b101000 =
b101000 a
b101000 ("
b1100100000 W
b10100 ^
b111100 X
b10100 7
b10100 `
b10100 r
b0 &
b0 %"
b111100 :
b111100 w
b111100 &"
b111 %
b111 #"
b10100 3
b10100 s
b10100 |
b10100 *"
b10100 2
b10100 )"
09
1A
1o
0;
0p
b11 K
b11 ~
b11111000010100 (
b11111000010100 )
0.
1*
b10 '
b10 h
b11 L
b1011111000010100 C
b1011111000010100 e
b10110 6
b10110 {
b11 >
b11 y
b10 ?
b10 f
b10 z
b10 }
b10 !"
b10 ""
1!
#300
0!
#350
1#
b1111111111111111010 T
b1010 :
b1010 w
b1010 &"
b101 <
b101 c
b101 t
b101 '"
b100 _
b110 ]
b101 =
b101 a
b101 ("
b1 Z
b11001 [
b1010 G
b1010 Y
b1010 b
b1010 u
b0 V
b101 U
b101 S
b10 $
b10 $"
b10 %
b10 #"
b11001 W
b0 ^
b1010 X
b101 7
b101 `
b101 r
b11 3
b11 s
b11 |
b11 *"
b11 2
b11 )"
1F
1k
0A
0o
0H
b110 K
b110 ~
b1001000000011 (
b1001000000011 )
0*
11
b11 '
b11 h
b110 L
b1101001000000011 C
b1101001000000011 e
bx @
bx d
bx v
b110 6
b110 {
b100 >
b100 y
b11 ?
b11 f
b11 z
b11 }
b11 !"
b11 ""
1!
#400
0!
#450
b0 U
b0 :
b0 w
b0 &"
b0 7
b0 `
b0 r
b0 Z
b0 [
b0 G
b0 Y
b0 b
b0 u
b1111111111111111111 T
b0 V
b0 S
b0 <
b0 c
b0 t
b0 '"
b1111111111111111111 _
b1 ]
b0 W
b0 ^
b0 X
b0 =
b0 a
b0 ("
b0 $
b0 $"
b0 %
b0 #"
0#
b0 3
b0 s
b0 |
b0 *"
b0 2
b0 )"
b10 D
b10 g
b10 m
1B
1n
0F
0k
b1000 K
b1000 ~
b1000 (
b1000 )
01
1-
b101 '
b101 h
b1000 L
b10100000000001000 C
b10100000000001000 e
b110 6
b110 {
b111 >
b111 y
b110 ?
b110 f
b110 z
b110 }
b110 !"
b110 ""
1!
#500
0!
#550
b1111 :
b1111 w
b1111 &"
b1111 G
b1111 Y
b1111 b
b1111 u
b1 Z
b1111 [
b1111111111111111010 T
b110 V
b111 U
b1 S
b1111 W
b11 7
b11 `
b11 r
b10 J
b10 Q
b10 R
b100 _
b110 ]
b10 ^
b1000 X
b101 =
b101 a
b101 ("
b11 <
b11 c
b11 t
b11 '"
b10 5
b10 O
b10 %
b10 #"
b1001 K
b1001 ~
b1 &
b1 %"
b11 $
b11 $"
b10 4
b1001 L
b0 D
b0 g
b0 m
0B
0n
1;
1p
b101001100010 (
b101001100010 )
1,
0-
b0 '
b0 h
b101001100010 C
b101001100010 e
b1000 6
b1000 {
b1001 >
b1001 y
b1000 ?
b1000 f
b1000 z
b1000 }
b1000 !"
b1000 ""
1!
#600
0!
#650
b0 :
b0 w
b0 &"
b0 Z
b0 [
b1111111111111111111 T
b0 V
b0 U
b0 S
b0 7
b0 `
b0 r
b0 G
b0 Y
b0 b
b0 u
b1111111111111111111 _
b1 ]
b0 W
b0 ^
b0 X
b0 =
b0 a
b0 ("
b0 <
b0 c
b0 t
b0 '"
b0 J
b0 Q
b0 R
b0 %
b0 #"
b0 &
b0 %"
b0 $
b0 $"
b0 4
b0 5
b0 O
18
1q
1B
1n
0;
0p
bx K
bx ~
b0 (
b0 )
0,
1+
b111 '
b111 h
bx L
b11100000000000000 C
b11100000000000000 e
b1001 6
b1001 {
b1010 >
b1010 y
b1001 ?
b1001 f
b1001 z
b1001 }
b1001 !"
b1001 ""
1!
#700
0!
#750
x\
bx :
bx w
bx &"
bx Z
bx [
bx G
bx Y
bx b
bx u
bx T
bx V
bx U
bx S
bx 7
bx `
bx r
bx J
bx Q
bx R
bx _
bx ]
bx W
bx ^
bx X
bx =
bx a
bx ("
bx <
bx c
bx t
bx '"
bx 5
bx O
bx %
bx #"
x#
bx 3
bx s
bx |
bx *"
bx 2
bx )"
bx &
bx %"
bx $
bx $"
bx 4
08
0q
0B
0n
b0xxxxxxxxxxxxxx (
bx )
x,
x.
x*
x1
x0
x-
x/
x+
bx '
bx h
bx K
bx ~
bx C
bx e
bx L
bx 6
bx {
bx >
bx y
bx ?
bx f
bx z
bx }
bx !"
bx ""
b1111 M
1!
